sharelatex/__init__.py
sharelatex/__version__.py
sharelatex/admin.py
sharelatex/cli.py
sharelatex-1.1.1.dist-info/licenses/LICENSE
sharelatex-1.1.1.dist-info/METADATA
sharelatex-1.1.1.dist-info/WHEEL
sharelatex-1.1.1.dist-info/entry_points.txt
sharelatex-1.1.1.dist-info/top_level.txt
sharelatex-1.1.1.dist-info/RECORD
